{
"meta":{"test_sets":["test"],"test_metrics":[{"best_value":"Min","name":"MultiClass"}],"learn_metrics":[{"best_value":"Min","name":"MultiClass"}],"launch_mode":"Train","parameters":"","iteration_count":1000,"learn_sets":["learn"],"name":"experiment"},
"iterations":[
{"learn":[4.070847051],"iteration":0,"passed_time":7.211336076,"remaining_time":7204.12474,"test":[4.071041595]},
{"learn":[3.784423418],"iteration":1,"passed_time":15.11065617,"remaining_time":7540.217429,"test":[3.786105735]},
{"learn":[3.571043654],"iteration":2,"passed_time":23.10762519,"remaining_time":7679.434104,"test":[3.573458254]},
{"learn":[3.392795393],"iteration":3,"passed_time":31.89075086,"remaining_time":7940.796964,"test":[3.395913453]},
{"learn":[3.252857577],"iteration":4,"passed_time":40.73249742,"remaining_time":8105.766987,"test":[3.255918854]},
{"learn":[3.14399618],"iteration":5,"passed_time":49.18005995,"remaining_time":8147.496598,"test":[3.147606031]},
{"learn":[3.03057526],"iteration":6,"passed_time":59.14834237,"remaining_time":8390.614853,"test":[3.035373665]},
{"learn":[2.935920066],"iteration":7,"passed_time":69.48262327,"remaining_time":8615.845286,"test":[2.940926597]},
{"learn":[2.85295546],"iteration":8,"passed_time":80.56963023,"remaining_time":8871.611506,"test":[2.85911471]},
{"learn":[2.766654348],"iteration":9,"passed_time":93.58897905,"remaining_time":9265.308926,"test":[2.773463636]},
{"learn":[2.68778351],"iteration":10,"passed_time":107.885905,"remaining_time":9699.923638,"test":[2.695077881]},
{"learn":[2.608268989],"iteration":11,"passed_time":122.6292381,"remaining_time":10096.47394,"test":[2.616223449]},
{"learn":[2.538414585],"iteration":12,"passed_time":137.4611811,"remaining_time":10436.47583,"test":[2.547027044]},
{"learn":[2.465402375],"iteration":13,"passed_time":151.8432997,"remaining_time":10694.10668,"test":[2.475038822]},
{"learn":[2.415750566],"iteration":14,"passed_time":164.3929022,"remaining_time":10795.13391,"test":[2.425661346]},
{"learn":[2.356740477],"iteration":15,"passed_time":176.0692283,"remaining_time":10828.25754,"test":[2.367791287]},
{"learn":[2.304155564],"iteration":16,"passed_time":186.4858103,"remaining_time":10783.26774,"test":[2.315520699]},
{"learn":[2.250376877],"iteration":17,"passed_time":196.6434595,"remaining_time":10727.99318,"test":[2.263175894]},
{"learn":[2.199998869],"iteration":18,"passed_time":207.0251919,"remaining_time":10689.03754,"test":[2.213169957]},
{"learn":[2.153707542],"iteration":19,"passed_time":217.8081556,"remaining_time":10672.59962,"test":[2.167489329]},
{"learn":[2.117667607],"iteration":20,"passed_time":229.6651928,"remaining_time":10706.77256,"test":[2.131851852]},
{"learn":[2.075017691],"iteration":21,"passed_time":243.6333094,"remaining_time":10830.60803,"test":[2.090030104]},
{"learn":[2.037311186],"iteration":22,"passed_time":259.5483123,"remaining_time":11025.16092,"test":[2.053402099]},
{"learn":[2.001207145],"iteration":23,"passed_time":274.8283486,"remaining_time":11176.35284,"test":[2.017940922]},
{"learn":[1.969546562],"iteration":24,"passed_time":288.6641652,"remaining_time":11257.90244,"test":[1.987091762]},
{"learn":[1.944017897],"iteration":25,"passed_time":300.8016489,"remaining_time":11268.49254,"test":[1.962000788]},
{"learn":[1.916982887],"iteration":26,"passed_time":311.7588337,"remaining_time":11234.86464,"test":[1.93572851]},
{"learn":[1.890002417],"iteration":27,"passed_time":321.9566088,"remaining_time":11176.49371,"test":[1.909212222]},
{"learn":[1.865182421],"iteration":28,"passed_time":332.1890584,"remaining_time":11122.60606,"test":[1.88562938]},
{"learn":[1.837808846],"iteration":29,"passed_time":343.4360694,"remaining_time":11104.43291,"test":[1.859155524]}
]}